npm_login/__init__.py
npm_login/api.py
npm_login/io.py
npm_login/logger.py
npm_login/npmrc.py
npm_login/utils.py
npm_login-0.1.2.dist-info/WHEEL
npm_login-0.1.2.dist-info/entry_points.txt
npm_login-0.1.2.dist-info/METADATA
npm_login-0.1.2.dist-info/RECORD
