Metadata-Version: 2.4
Name: npm-login
Version: 0.1.2
Summary: Simulates `npm login` command behavior with support only for legacy authentication
Keywords: npm,yarn,node,nodejs,authentication,login
Author: Vyacheslav Konovalov
Author-email: Vyacheslav Konovalov <crabvk@protonmail.com>
License-Expression: MIT
Classifier: Environment :: Console
Classifier: Operating System :: OS Independent
Classifier: Intended Audience :: Developers
Classifier: Programming Language :: Python :: 3
Requires-Python: >=3.13
Project-URL: Homepage, https://github.com/crabvk/npm-login
Project-URL: Repository, https://github.com/crabvk/npm-login.git
